LICENSE
MANIFEST.in
README.rst
setup.py
django_rmixins.egg-info/PKG-INFO
django_rmixins.egg-info/SOURCES.txt
django_rmixins.egg-info/dependency_links.txt
django_rmixins.egg-info/not-zip-safe
django_rmixins.egg-info/top_level.txt
rmixins/__init__.py
rmixins/mixins.py
rmixins/models.py